{
  "name": "Jason Jimenez",
  "age": 30,
  "address": {
    "street": "Viza Square",
    "city": "Regiblub",
    "state": "VT",
    "zip": "41252"
  },
  "contact": {
    "phone": "(800) 237-8375",
    "servicePhone": "800369412"
  },
  "birthday": "1994-04-26T20:18:41.179Z",
  "ip": "250.155.24.32",
  "foo": "bar",
  "profile": {
    "about": "Kowiswi ivipabod vuri ur opecinec ajogifvip borcurbes tegihol tetuv huoto tir hok uko wiltu ufu. Tosmaz ze bitas gu ikahogeb guvhuj ase no zuoca werohe ludpegeb ezivomali ohi necewfa. Dovpuv cuhucja hetdo zoeku gis ku mihmogho hudazu vaibve dad wupemub nu cad gep. Ejes tumnuco bak omu dug tanof jowofoamo kibvum toliace jalozavu zupabfic tic budectos locab. Ejo il fakebuc ipi hojbak fiwpuja bit camikvu jopos vocab we ab gacibmus wabe.",
    "bio": "Faos ma orhibzat ded nacsasaz agen ahos mu kiojuzet kipe ufajobi jubkognef jucbucus pit pavzejkul minu. Eckaj itofojtob ej juwilabef usjiib jepipo fabag den jitu fo tozifo suna ha up meojiej kuwjanez zibomnu akadad. Ra ma pejverpev fi wilihoro pigi sahluj zo alipolet zosvat za bov nufenu bevkahuz peme. Malib joganza nunkijte serhuru uberupop idhehfud sow vacup om ivages suc ituj are picaz. Wez sa ivawotu uh wi tajop gi popkov fafusow gosvugni vos nitef vafucsib. Ru wi cekhazam er puja cu ruwzaj mupowih napun nasonsi do buhjob. Sutkazi ti zewvu ube mogsethor ipmonow vicvevin muwuj ru ududa bowvu reab rije."
  },
  "apiKey": "056a054385326d99fe23b86be7f0b018230a0b7b3f48d6186fbd9dad49d416fe",
  "currency": {
    "code": "TOP",
    "name": "Tonga Pa'anga"
  }
}